database2prompt/__init__.py
database2prompt/database/core/database_config.py
database2prompt/database/core/database_factory.py
database2prompt/database/core/database_params.py
database2prompt/database/core/database_strategy.py
database2prompt/database/core/metadata.py
database2prompt/database/pgsql/postgresql_strategy.py
database2prompt/database/processing/database_processor.py
database2prompt/json_generator/__init__.py
database2prompt/json_generator/json_generator.py
database2prompt/main.py
database2prompt/markdown/markdown_generator.py
database2prompt-0.2.0.dist-info/LICENSE
database2prompt-0.2.0.dist-info/METADATA
database2prompt-0.2.0.dist-info/WHEEL
database2prompt-0.2.0.dist-info/RECORD
