Metadata-Version: 2.3
Name: database2prompt
Version: 0.2.0
Summary: Extract relevant metadata from databases and transform it into context for Retrieval-Augmented Generation (RAG) in generative AI applications.
Author: jose.neto
Author-email: jose.neto-ext@anbima.com.br
Requires-Python: >=3.12
Classifier: Programming Language :: Python :: 3
Classifier: Programming Language :: Python :: 3.12
Classifier: Programming Language :: Python :: 3.13
Requires-Dist: psycopg2-binary (>=2.9.10,<3.0.0)
Requires-Dist: pytest (>=8.3.4,<9.0.0)
Requires-Dist: python-dotenv (>=1.1.0,<2.0.0)
Requires-Dist: sqlalchemy (>=2.0.37,<3.0.0)
